riboplot/__init__.py
riboplot/config.py
riboplot/ribocore.py
riboplot/ribocount.py
riboplot/riboplot.py
riboplot/data/ribocount.html
riboplot/data/ribocount_index.html
riboplot/data/ribocount_prime.html
riboplot/data/riboplot.html
riboplot/data/css/asc.gif
riboplot/data/css/bg.gif
riboplot/data/css/custom.css
riboplot/data/css/desc.gif
riboplot/data/css/normalize.css
riboplot/data/css/skeleton.css
riboplot/data/js/custom.js
riboplot/data/js/jquery-1.11.3.min.js
riboplot/data/js/jquery-1.11.3.min.map
riboplot/data/js/jquery.tablesorter.min.js
riboplot/scripts/plot_color_schemes.sh
riboplot/scripts/plot_multiple.sh
riboplot/scripts/run_coverage.sh
riboplot/scripts/run_ribocount_sample.sh
riboplot/scripts/run_riboplot_sample.sh
riboplot/scripts/run_tests.sh
riboplot-0.3.1.dist-info/DESCRIPTION.rst
riboplot-0.3.1.dist-info/METADATA
riboplot-0.3.1.dist-info/RECORD
riboplot-0.3.1.dist-info/WHEEL
riboplot-0.3.1.dist-info/entry_points.txt
riboplot-0.3.1.dist-info/metadata.json
riboplot-0.3.1.dist-info/top_level.txt
