Metadata-Version: 2.0
Name: riboplot
Version: 0.3.1
Summary: Plot read counts of RiboSeq data from BAM format alignment files
Home-page: https://github.com/vimalkvn/riboplot
Author: Vimalkumar Velayudhan
Author-email: vimalkumarvelayudhan@gmail.com
License: GPL
Keywords: riboplot
Platform: UNKNOWN
Classifier: Development Status :: 4 - Beta
Classifier: Intended Audience :: Science/Research
Classifier: Topic :: Scientific/Engineering :: Bio-Informatics
Classifier: License :: OSI Approved :: GNU General Public License (GPL)
Classifier: Natural Language :: English
Classifier: Programming Language :: Python :: 2
Classifier: Programming Language :: Python :: 2.6
Classifier: Programming Language :: Python :: 2.7
Requires-Dist: matplotlib (<=1.4.3)
Requires-Dist: mock (==1.0.1)
Requires-Dist: pysam (<=0.8.3)
